dwavebinarycsp/__init__.py
dwavebinarycsp/exceptions.py
dwavebinarycsp/package_info.py
dwavebinarycsp/reduction.py
dwavebinarycsp/testing.py
dwavebinarycsp/compilers/__init__.py
dwavebinarycsp/compilers/stitcher.py
dwavebinarycsp/core/__init__.py
dwavebinarycsp/core/constraint.py
dwavebinarycsp/core/csp.py
dwavebinarycsp/factories/__init__.py
dwavebinarycsp/factories/constraint/__init__.py
dwavebinarycsp/factories/constraint/gates.py
dwavebinarycsp/factories/constraint/sat.py
dwavebinarycsp/factories/csp/__init__.py
dwavebinarycsp/factories/csp/circuits.py
dwavebinarycsp/factories/csp/sat.py
dwavebinarycsp/io/__init__.py
dwavebinarycsp/io/cnf.py
dwavebinarycsp-0.3.0.dist-info/LICENSE
dwavebinarycsp-0.3.0.dist-info/METADATA
dwavebinarycsp-0.3.0.dist-info/WHEEL
dwavebinarycsp-0.3.0.dist-info/top_level.txt
dwavebinarycsp-0.3.0.dist-info/RECORD
