Metadata-Version: 2.1
Name: dwavebinarycsp
Version: 0.3.0
Summary: Solves constraints satisfaction problems with binary quadratic model samplers
Home-page: https://github.com/dwavesystems/dwavebinarycsp
Author: D-Wave Systems Inc.
Author-email: tools@dwavesys.com
License: Apache 2.0
Project-URL: Changes, https://github.com/dwavesystems/dwavebinarycsp/releases
Project-URL: Documentation, https://docs.ocean.dwavesys.com
Project-URL: Souce Code, https://github.com/dwavesystems/dwavebinarycsp
Classifier: License :: OSI Approved :: Apache Software License
Classifier: Operating System :: OS Independent
Classifier: Programming Language :: Python :: 3 :: Only
Classifier: Programming Language :: Python :: 3.8
Classifier: Programming Language :: Python :: 3.9
Classifier: Programming Language :: Python :: 3.10
Classifier: Programming Language :: Python :: 3.11
Classifier: Programming Language :: Python :: 3.12
Requires-Python: >=3.8
License-File: LICENSE
Requires-Dist: penaltymodel>=1.0.0
Requires-Dist: networkx>=2.4
Requires-Dist: dimod>=0.10.9
Provides-Extra: mip
Provides-Extra: maxgap
